phonenumbers/__init__.py
phonenumbers/__init__.pyi
phonenumbers/asyoutypeformatter.py
phonenumbers/asyoutypeformatter.pyi
phonenumbers/carrier.py
phonenumbers/carrier.pyi
phonenumbers/geocoder.py
phonenumbers/geocoder.pyi
phonenumbers/phonemetadata.py
phonenumbers/phonemetadata.pyi
phonenumbers/phonenumber.py
phonenumbers/phonenumber.pyi
phonenumbers/phonenumbermatcher.py
phonenumbers/phonenumbermatcher.pyi
phonenumbers/phonenumberutil.py
phonenumbers/phonenumberutil.pyi
phonenumbers/prefix.py
phonenumbers/prefix.pyi
phonenumbers/py.typed
phonenumbers/re_util.py
phonenumbers/re_util.pyi
phonenumbers/shortnumberinfo.py
phonenumbers/shortnumberinfo.pyi
phonenumbers/timezone.py
phonenumbers/timezone.pyi
phonenumbers/unicode_util.py
phonenumbers/unicode_util.pyi
phonenumbers/util.py
phonenumbers/util.pyi
phonenumbers/carrierdata/__init__.py
phonenumbers/carrierdata/__init__.pyi
phonenumbers/carrierdata/data0.py
phonenumbers/carrierdata/data1.py
phonenumbers/carrierdata/data2.py
phonenumbers/data/__init__.py
phonenumbers/data/__init__.pyi
phonenumbers/data/alt_format_255.py
phonenumbers/data/alt_format_27.py
phonenumbers/data/alt_format_30.py
phonenumbers/data/alt_format_31.py
phonenumbers/data/alt_format_34.py
phonenumbers/data/alt_format_350.py
phonenumbers/data/alt_format_351.py
phonenumbers/data/alt_format_352.py
phonenumbers/data/alt_format_358.py
phonenumbers/data/alt_format_359.py
phonenumbers/data/alt_format_36.py
phonenumbers/data/alt_format_372.py
phonenumbers/data/alt_format_373.py
phonenumbers/data/alt_format_380.py
phonenumbers/data/alt_format_381.py
phonenumbers/data/alt_format_385.py
phonenumbers/data/alt_format_39.py
phonenumbers/data/alt_format_43.py
phonenumbers/data/alt_format_44.py
phonenumbers/data/alt_format_49.py
phonenumbers/data/alt_format_505.py
phonenumbers/data/alt_format_506.py
phonenumbers/data/alt_format_52.py
phonenumbers/data/alt_format_54.py
phonenumbers/data/alt_format_55.py
phonenumbers/data/alt_format_58.py
phonenumbers-8.13.27.dist-info/LICENSE
phonenumbers-8.13.27.dist-info/METADATA
phonenumbers-8.13.27.dist-info/WHEEL
phonenumbers-8.13.27.dist-info/top_level.txt
phonenumbers-8.13.27.dist-info/RECORD
